topsis/102203557.py
topsis/__init__.py
Topsis_Chahat_Garg_102203557-0.1.0.dist-info/LICENSE
Topsis_Chahat_Garg_102203557-0.1.0.dist-info/METADATA
Topsis_Chahat_Garg_102203557-0.1.0.dist-info/WHEEL
Topsis_Chahat_Garg_102203557-0.1.0.dist-info/top_level.txt
Topsis_Chahat_Garg_102203557-0.1.0.dist-info/RECORD
