Metadata-Version: 2.2
Name: Topsis-Chahat_Garg-102203557
Version: 0.1.0
Summary: A Python package for implementing the TOPSIS method.
Home-page: https://github.com/chahatgarg884/Topsis-102203557-Chahat_Garg
Author: Chahat Garg
Author-email: gargchahat2005@gmail.com
Classifier: Programming Language :: Python :: 3
Classifier: License :: OSI Approved :: MIT License
Classifier: Operating System :: OS Independent
Requires-Python: >=3.6
License-File: LICENSE
Requires-Dist: numpy
Requires-Dist: pandas
Dynamic: author
Dynamic: author-email
Dynamic: classifier
Dynamic: description
Dynamic: description-content-type
Dynamic: home-page
Dynamic: requires-dist
Dynamic: requires-python
Dynamic: summary
